tec/__init__.py
tec/ic/__init__.py
tec/ic/ia/__init__.py
tec/ic/ia/pc2/__init__.py
tec/ic/ia/pc2/g07/__init__.py
tec/ic/ia/pc2/g07/main.py
tec/ic/ia/pc2/g07/algorithms/A_Star.py
tec/ic/ia/pc2/g07/algorithms/Algorithm.py
tec/ic/ia/pc2/g07/algorithms/Genetic.py
tec/ic/ia/pc2/g07/algorithms/__init__.py
tec/ic/ia/pc2/g07/algorithms/Genetic_Classes/CrossOver.py
tec/ic/ia/pc2/g07/algorithms/Genetic_Classes/Individual.py
tec/ic/ia/pc2/g07/algorithms/Genetic_Classes/Random_CrossOver.py
tec/ic/ia/pc2/g07/algorithms/Genetic_Classes/Sons_of_Sons_CrossOver.py
tec/ic/ia/pc2/g07/algorithms/Genetic_Classes/__init__.py
tec/ic/ia/pc2/g07/unit_tests/__init__.py
tec/ic/ia/pc2/g07/unit_tests/test_A_Star.py
tec/ic/ia/pc2/g07/unit_tests/test_GA.py
tec.ic.ia.pc2.g07.main-1.0.0.dist-info/METADATA
tec.ic.ia.pc2.g07.main-1.0.0.dist-info/RECORD
tec.ic.ia.pc2.g07.main-1.0.0.dist-info/WHEEL
tec.ic.ia.pc2.g07.main-1.0.0.dist-info/top_level.txt
