Metadata-Version: 2.1
Name: tec.ic.ia.pc2.g07.main
Version: 1.0.0
Summary: This reposiory contains the Artificial Intelligence's short-project 2 and 3. Course imparted on Instituto Tecnologico de Costa Rica by Juan Esquivel. On this project we will explore search algorithms to solve path-finding problems.
Home-page: https://github.com/mamemo/Path-finding
Author: Trifuerza
Author-email: UNKNOWN
License: UNKNOWN
Platform: UNKNOWN
